{"uUT3YlfBxgNrXQTxgBNw2A==":"jm_logo_sq-500x500.png","5ktGGzAm8Om51Bun5bB7Xg==":"mbr-1364x1080.jpg","27HU5ksFiMPsuABZihC9UA==":"mbr-1620x1080.jpg","lP7Z2Uywq1WMEv/w2sJ3fQ==":"mbr-1-1620x1080.jpg","iCPSaFHhxg4EjgVkLyHFuQ==":"cd_cover_ex-270x270.jpg","roNKkHSqYGlPkNcRzLZy+Q==":"jule%20malischke-1478-2000x1333.jpg","MPmewseSRlMv5zGwSiD2Pg==":"banner2-1440x900.jpg","EdMOXhoxIWxcof5WdcEGVQ==":"banner3-1440x900.jpg","Datx4f8tu6mqBilrtZEKdQ==":"banner_try3-960x522.jpg","rxIg64zW5rZL8ZKxa6Jd+A==":"banner3-1-1440x900.jpg","kV0iYFnDUUpSJ3mGysBafQ==":"banner3-2-1440x900.jpg","t9te8xsawYlSlUsooc1MDw==":"mbr-1618x1080.jpg","B6mdCN9f7AFxEpahomqhyQ==":"jule_a4_bg-912x1290.jpg","WUJsR8yH42Fly81hXB5K8g==":"mbr-720x1080.jpg","je+crHZCy8sH25Whya2bIg==":"mbr-4-1620x1080.jpg","CQX11lJ5YBvFWQ6gtRQGnA==":"banner_try3-1-960x522.jpg","wy/LKxLqjPdq4iu8nCcDug==":"banner3-3-1440x900.jpg","MKT3/GO3vBpmN2cobSepmQ==":"mbr-5-1620x1080.jpg","asAM8l8qkkuKkeaPXwdkjg==":"mbr-6-1620x1080.jpg","Z5UjmMCQcedLT6GqZOOQ4w==":"banner_try3-2-960x522.jpg","aRDXxy8D90o+GSl6EvCIpQ==":"banner3-4-1440x900.jpg","CGGtf1MuvLFB/KUrA/+mag==":"jumbotron.jpg","pGOqDazkUnoCTRG5EbKFjw==":"img-7449-1440x960.jpg","pM0Qt8GmH6IoDCp/3d9TGw==":"img-7450-2000x1311.jpg","ww05hQSqZf/Mseu1a7nfWg==":"mbr-7-1620x1080.jpg","+2336HZDLQb1JysOWPJsLA==":"jm_green-500x500.png","8SC1vKZzpclnmciGpbg/hA==":"jm_green-1-500x500.png","xuN2kkum7iSXGgNDk5IwaA==":"jm-blue-1-122x122.png","drZBApgkie+LrKQfQip5Dg==":"mbr-847x1080.jpg","L+7eMgSfpJICTxD94JjA2w==":"mbr-715x1080.jpg","ihQ8jvjPXuNYfMqOtWgbPQ==":"mbr-720x1080.jpg","LzBNipNCcYgPd3CQHbzZdg==":"img-7450-1440x960.jpg","P78Stl4jOcOcj+rEYlgIew==":"mbr-1-1620x1080.jpg","Bu0I4uEkDj7YJHsNHHo1Zw==":"mbr-1-720x1080.jpg","ujgMWFTMWgQK++OLTYAWhw==":"thomas-3-450x526.png","1Tb1TH6UvV+Bnol1MOAMZg==":"mbr-1-608x1080.jpg","17opjCAipAtQsDk3TGTeMQ==":"mbr-2-720x1080.jpg","gZN5EIuonz/YLw1FSLJDrw==":"mbr-5-720x1080.jpg","SBi8GQW/S8WnJXy5rqSC1g==":"mbr-864x1080.jpg","n9plHQ1pd1tEjf4Cv7FaLw==":"mbr-4-1620x1080.jpg","8/gpOh6L92zEVAOtJ8Fqcg==":"bild%203-1086x968.jpg","YwP1heQCKY/3ILnJm6E5yg==":"mbr-6-720x1080.jpg","JGdL2reKCVoedKpHLmqyKw==":"mbr-7-720x1080.jpg","eL/DlWTwnWFuR2fAvv9qyg==":"elixir-440x440.jpg","Tq1ZeFdBI8FPzqi5B7ODYg==":"elixir_dark-440x440.jpg","mEWi961CjA14y50X4+x1cw==":"elixir_dark-1-440x440.jpg","j5KTLrjHxnoXxjFKtGXUUA==":"savarez-2.gif","JFMoGEa0vgHBZKkXBHSwww==":"acus-676x676.png","Os1hpkyKHdJTZJYYSjSiXg==":"01.jpg","0OOE1Usrtktm437Z/qTMRQ==":"background2.jpg","DtHhloO/MKJjPHxrUjbvKg==":"linda-320x213.jpg","nCbNdx4VnVYL81NaGSH1hw==":"ralle-320x213.jpg","6IJ87ZkbohxlAa5HGTLDaw==":"olivia-1-320x213.jpg","EsNfS3+G0vMQgfOp2d+y0A==":"br-676x845.jpg","uWTh5mtm7GM5lRdFoY1Hyw==":"siglinde-1-676x451.jpg","xMMC0AxXUSIyiRZdkqqHiQ==":"siglinde-2-676x451.jpg","9nebL1M79LgmKuBqsgO8KQ==":"yairi-676x451.jpg","lFNJzosCMF5lO6UZaV13nA==":"siglinde-3-676x451.jpg","vQA7U/hKILG+d2MyQjvD2g==":"br-2-676x845.jpg","yFR8MZekREWPVyK8IsD6Qw==":"olivia-676x451.jpg","x+v5ndCy4ERhJjzHLtEDyA==":"br-3-676x845.jpg","QXEU+XSIM+ybOTahsMGg6A==":"siglinde-4-676x451.jpg","1gXCsggU57XrFqDrNONOog==":"img-2540-676x451.jpg","vcSx98kfmc5eA6cWr2rqSA==":"photo%20christian%20debus%204%20poster-1200x800.jpg","M5AxCQLAQRxCEiXoMw0TsA==":"photo%20christian%20debus%20press%205-1200x1800.jpg","kG3jCS6CKvkYWi4GGFR1JA==":"photo%20christian%20debus%20press%205-1200x1800.jpg","0kaHC/atYB/Mvyjs4yJvmw==":"gitarrenfestival-2018-2000x473.jpg","7R69VI5muJ6oE8uh3TLg7w==":"gitarrenfestival-2018-2583x611.jpg","cOaag5h3gBXY1LUYA11W6w==":"gitarrenfestival-2017-2583x611.jpg","HtrOzKEWFg7YgHpEJph8ZQ==":"gitarrenfestival-2019-2583x611.jpg","xFumqPZTws/ORd5yJe3FZA==":"01-1.jpg","GmGRMlyJMvVcJlvJZuDJVA==":"background2-1.jpg","PdMhXTnfigh0XDaKZAeXQA==":"02.jpg","ciCB1zR32p7f+CfMc2hA2Q==":"03.jpg","xK8RJtrkCPLdAits7oJJMg==":"06.jpg","oI0A2s0mjAbh/WlDWiV60g==":"05.jpg","Fp3mX3XLZm/DkCMmvStqHw==":"background5.jpg","9haNBdnh24l6Ek52k8Aftg==":"04.jpg","N6aGfaaFcmg0jze/e3ucwA==":"album%202-344x700.jpg","9L7GEm9WIh6yOrrEaefCsA==":"photo%20christian%20debus%204%20poster-1200x800.jpg","/YLYGOeTB035MV0XoGycow==":"07-7.jpg","c+ZB3u8m9PiEpgdA98dfuA==":"08-8.jpg","V/qljpA5OWLlxH2c41jTmQ==":"photo%20malte%20stro%CC%88msdorfer%20-2000x1336.jpg","2h8xTfHmGxdOjrl2bm64ZA==":"contact%20image-2000x1333.jpg","3LvQgTaqGaIBfXZ9b4TJng==":"2017-05-27%2018.48.27-2-2000x3276.jpg","kT2PmMolVUeYn2d7ZgVEvg==":"2017-05-27%2018.48.27-2-2000x3276.jpg","LiUIORYxGXGMpCM1i0NnEA==":"06-1.jpg","iqw7yQD1OsBIxUDxW8kJ2w==":"07.jpg","OY9LOWU65Ne1Kvrh75200Q==":"05-1.jpg","SqMBlm4eUHGA9C8A4ie2nQ==":"01-2.jpg","7ZTB0MH1zI/N08WgtM8fnw==":"06-2.jpg","BaokzyGhZkQRMLWHGuUSAg==":"background6.jpg","zLh0t5E3/MfA738j9JpYIQ==":"duo_jule_isa-866x582.png","ib5teyjGtgdu2KeWiTHRjg==":"jule_isa%20photo%20malte%20stro%CC%88msdorfer%20-866x568.jpg","JRLEU6Z5mx3V0cqWIdjUnw==":"photo%20christian%20debus-866x577.jpg","gJNrsLvYa/uOgF3uvtBdwA==":"phot%20christian%20debus%20press-866x577.jpg","0i+kbH6ADLwzjoFW0/26LQ==":"jule_isa%20photo%20malte%20stro%CC%88msdorfer%20-866x568.jpg","vcXtpSRnSh2/utgUc2VsaQ==":"jule%20027-866x576.jpg","737UykEbO4aPvhweFyU3lg==":"cover%20jule%203000x3000%20pix-662x662.jpg","PNiHjsZAccjUkGNh15heXg==":"cover%20jule%203000x3000%20pix-982x982.jpg","Ly+mdm63lVz6CqSX2vcU6g==":"background3.jpg","jY+jWX29CU6db/AwiTalyw==":"teaching-800x533.jpg","Tarooe6Qp5L9+VEuhcCBCg==":"teaching-1-800x533.jpg","QSz27w4H047vYp7qQeswGA==":"photo%20christan%20debus%201-436x654.jpg","lR5aZLowBvBAwSbX6BU+vA==":"mobirise2018118_125472018-11-6_14-2-11.jpg","n1vqgVB7/GgpSxpuq8uSDQ==":"mobirise2018118_125472018-11-6_14-5-27.jpg","hI3kZMUmGz6w4Klr2LRQJg==":"mobirise2018118_125472018-11-6_14-6-41.jpg","/q29wZ+9djS4rNQxyryTJw==":"mobirise2018118_125472018-11-6_14-7-25.jpg","2MLJo/wX3TcEmVNiT/mFZA==":"mobirise2018118_125472018-11-6_14-8-18.jpg","FjWF0mWVGTc/MA8HGlYYUQ==":"mobirise2018118_125472018-11-6_14-15-33.jpg","XdHGBpKFD4pQ+v45orM/VQ==":"mobirise2018118_125472018-11-6_14-16-15.jpg","0xD3JlvxioeFsnoMZa6kcA==":"mobirise2018118_125472018-11-6_14-18-30.jpg","M1R5MJKZoqN6F8M/X+lUZQ==":"mobirise2018118_125472018-11-6_14-19-16.jpg","ha9gQi1usHCJXxx1Dg4FpA==":"mobirise2018118_125472018-11-6_14-20-3.jpg","ZOQN2Fwcm2U/QHl/Pdi4tQ==":"savarez.svg","L1Nkxc/xXZhc9G0Vj22MNw==":"elixir_logo-400x400.jpg","IL4WYNI0wq66mD3WUz6m9A==":"logo-savarez-300x300.jpg","3p2Y02BL+pY6pI7ey+Nl3Q==":"acus-200x200.png","s4fxIPdQd4rwJINMSXKOOw==":"savarez-logo-300x300.jpg","pBL8X7gAdC4rPI6QFLpg/g==":"g7_capo_logo-400x400.jpg","JT7YqXQ47pMeD8K0FkSMww==":"savarez-couleur-8cm-300x300.jpg","5AyEDu2Re7cWsx0Fzt1/fg==":"savarez-couleur-8cm-1-300x300.jpg","6fw0IqsSfMu6s3HiDCfA3g==":"ralle-1-320x213.jpg","/3mlH7ylYdS55H/Ojy7ouQ==":"ralle-2-320x213.jpg","dtNA79cfo7dztV3xDank7w==":"punky_josi-676x451.jpg","8b3ht1kCaqJIvz4BKUrlvA==":"punky_josi-1-676x451.jpg","9twvzOROa/1j4zCr+bikqQ==":"olivia-1-676x451.jpg","V7ChtcfPazQ1F4qnrY+/zQ==":"cristin-claas-436x291.jpg","YWe9vSkAqjuEdqxXwlymKw==":"tattoo-7-2000x1126.jpg","Xhsk1TPLD/0JkCdixOPvtQ==":"slide2-1600x900.jpg","kPlcAvQbVh/PbX0MPm9PNQ==":"bildschirmfoto%202018-11-17%20um%2021.50.31-601x397.png","JAgDJqXt5wFvJes47Keu9A==":"bildschirmfoto%202018-11-17%20um%2021.50.31-85x48.png","lmORVQ6raTlMneBKhS3ENw==":"bildschirmfoto%202018-11-20%20um%2023.57.46-597x397.png","GK+dDNYEYhB6Vx527gKkNA==":"bildschirmfoto%202018-11-20%20um%2023.57.46-85x48.png","iIDDA+2tJOEYnhDZCZKcPg==":"bildschirmfoto%202018-11-20%20um%2023.57.46-1024x576.jpg","CDA4c88A/9NGBcLwMiZNCw==":"bildschirmfoto%202018-11-20%20um%2023.57.46-1024x768.jpg","3XzeSF6yD7+0BlnIYcmINg==":"bildschirmfoto%202018-11-17%20um%2021.50.31-1024x768.jpg","4ymCK93PhjG0PMHcIrSPLg==":"bildschirmfoto%202018-11-20%20um%2023.57.34-600x401.png","mTO43N8A2MLyVGZgDvs1Mw==":"bildschirmfoto%202018-11-20%20um%2023.57.34-85x48.png","mSbPpAgwG0wJMZxItDUSBA==":"bildschirmfoto%202018-11-20%20um%2023.56.32-530x398.png","TC4PRTlUW+ShSK+lvhoG+Q==":"bildschirmfoto%202018-11-20%20um%2023.56.32-85x48.png","+lSRL/TmntZGj73sIdwalw==":"sweden%20summer%20camp%20(12)-1920x1080.png","+CvywXsPS9/8jfv0h74HKw==":"sweden%20summer%20camp%20(10)-1920x1080.png","XM9TuORfiOx06kJmkAhC+A==":"sweden%20summer%20camp%20(9)-1920x1080.png","IGrXvLo3Evg2E7bDW2hfHQ==":"sweden%20summer%20camp%20(9)-1920x1080.png","/9K4Bgb23ADjlz9A9eNcfA==":"sweden%20summer%20camp%20(9)-1920x1080.png","IHMvMUaRyZuSzIpJePnVXQ==":"sweden%20summer%20camp%20(2)-601x397.png","fXa3QPhNagyDKHra4fHREA==":"sweden%20summer%20camp%20(8)-1920x1080.png","GP6s/dI2qyPNB935MqMhrw==":"sweden%20summer%20camp%20(1)-1920x1080.png","qDDTkyP0Nti+ErdjWifneQ==":"sweden%20summer%20camp%20(6)-596x397.png","dqKC93XcvCrZcG/JMiuUcw==":"sweden%20summer%20camp%20(4)-530x398.png","j1qs1CxAs0mvtmLjJ22W1A==":"sweden%20summer%20camp%20(7)-594x393.png","ho9UnqxCn70ZKM/mrc1UUQ==":"sweden%20summer%20camp%20(3)-530x401.png","hPyw7I3qt5YI4HLyHRVowg==":"gitarrenfestival-2018-436x103.jpg","klLqq4gZRKTXD92NuXiRFw==":"gitarrenfestival-2020-2583x611.jpg"}